[{"text": "43", "coordinates": [1124, 728, 1191, 787], "confidence": 0.994, "entities": [["43", "CARDINAL"]], "pos": [["43", "NUM"]]}, {"text": "Bw", "coordinates": [2407, 980, 2465, 1025], "confidence": 0.141, "entities": [], "pos": [["Bw", "NOUN"]]}, {"text": "Que", "coordinates": [1459, 1077, 1609, 1179], "confidence": 0.07, "entities": [], "pos": [["Que", "NOUN"]]}, {"text": "em", "coordinates": [1611, 1090, 1716, 1188], "confidence": 0.762, "entities": [], "pos": [["em", "PRON"]]}, {"text": "what", "coordinates": [1750, 1102, 1918, 1201], "confidence": 0.98, "entities": [], "pos": [["what", "PRON"]]}, {"text": "they", "coordinates": [1924, 1115, 2107, 1212], "confidence": 0.986, "entities": [], "pos": [["they", "PRON"]]}, {"text": "want!", "coordinates": [2122, 1127, 2371, 1222], "confidence": 0.888, "entities": [], "pos": [["want", "VERB"], ["!", "PUNCT"]]}, {"text": "of", "coordinates": [1447, 1314, 1499, 1355], "confidence": 0.768, "entities": [], "pos": [["of", "ADP"]]}, {"text": "Winston", "coordinates": [1775, 1823, 1803, 1925], "confidence": 0.948, "entities": [["Winston", "GPE"]], "pos": [["Winston", "PROPN"]]}, {"text": "Cavalieri", "coordinates": [1910, 1890, 2085, 1943], "confidence": 0.16, "entities": [["Cavalieri", "ORG"]], "pos": [["Cavalieri", "NOUN"]]}, {"text": "Salem", "coordinates": [2148, 1900, 2297, 1970], "confidence": 0.666, "entities": [["Salem", "GPE"]], "pos": [["Salem", "NOUN"]]}, {"text": "The", "coordinates": [1333, 1969, 1372, 2007], "confidence": 0.994, "entities": [], "pos": [["The", "PRON"]]}, {"text": "largest-selling", "coordinates": [1378, 1971, 1537, 2014], "confidence": 0.886, "entities": [], "pos": [["largest", "ADJ"], ["-", "PUNCT"], ["selling", "NOUN"]]}, {"text": "cigarette", "coordinates": [1347, 2009, 1443, 2045], "confidence": 0.992, "entities": [], "pos": [["cigarette", "PROPN"]]}, {"text": "of", "coordinates": [1450, 2012, 1475, 2045], "confidence": 0.998, "entities": [], "pos": [["of", "ADP"]]}, {"text": "all!", "coordinates": [1481, 2012, 1524, 2044], "confidence": 0.798, "entities": [], "pos": [["all", "PRON"], ["!", "PUNCT"]]}, {"text": "Besureto", "coordinates": [1322, 2055, 1411, 2085], "confidence": 0.893, "entities": [], "pos": [["Besureto", "NOUN"]]}, {"text": "orderenough", "coordinates": [1414, 2055, 1545, 2091], "confidence": 0.991, "entities": [], "pos": [["orderenough", "VERB"]]}, {"text": "The", "coordinates": [1583, 2055, 1621, 2089], "confidence": 0.998, "entities": [], "pos": [["The", "PRON"]]}, {"text": "largest-selling", "coordinates": [1626, 2059, 1788, 2103], "confidence": 0.134, "entities": [], "pos": [["largest", "ADJ"], ["-", "PUNCT"], ["selling", "NOUN"]]}, {"text": "CIGARET", "coordinates": [1921, 2037, 2012, 2068], "confidence": 0.419, "entities": [], "pos": [["CIGARET", "PROPN"]]}, {"text": "Camels-the", "coordinates": [1323, 2081, 1440, 2108], "confidence": 0.302, "entities": [], "pos": [["Camels", "PROPN"], ["-", "PROPN"], ["the", "PRON"]]}, {"text": "most", "coordinates": [1444, 2082, 1490, 2109], "confidence": 0.621, "entities": [], "pos": [["most", "ADV"]]}, {"text": "ular", "coordinates": [1320, 2098, 1367, 2123], "confidence": 0.982, "entities": [], "pos": [["ular", "ADJ"]]}, {"text": "cigarette", "coordinates": [1371, 2099, 1469, 2125], "confidence": 0.993, "entities": [], "pos": [["cigarette", "PROPN"]]}, {"text": "in", "coordinates": [1472, 2099, 1498, 2125], "confidence": 0.998, "entities": [], "pos": [["in", "ADP"]]}, {"text": "the", "coordinates": [1502, 2099, 1543, 2126], "confidence": 0.998, "entities": [], "pos": [["the", "PRON"]]}, {"text": "filter", "coordinates": [1603, 2093, 1659, 2129], "confidence": 0.965, "entities": [], "pos": [["filter", "VERB"]]}, {"text": "cigarette!", "coordinates": [1665, 2097, 1777, 2134], "confidence": 0.991, "entities": [], "pos": [["cigarette", "PROPN"], ["!", "PUNCT"]]}, {"text": "Roger's", "coordinates": [1847, 2100, 1933, 2142], "confidence": 0.996, "entities": [["Roger", "PERSON"]], "pos": [["Roger", "PROPN"], ["'s", "PART"]]}, {"text": "favorite", "coordinates": [1936, 2106, 2022, 2146], "confidence": 0.887, "entities": [], "pos": [["favorite", "ADJ"]]}, {"text": "in", "coordinates": [2029, 2108, 2056, 2147], "confidence": 0.886, "entities": [], "pos": [["in", "ADP"]]}, {"text": "The", "coordinates": [2129, 2094, 2165, 2124], "confidence": 0.991, "entities": [], "pos": [["The", "PRON"]]}, {"text": "newest", "coordinates": [2171, 2094, 2249, 2126], "confidence": 0.995, "entities": [], "pos": [["newest", "ADJ"]]}, {"text": "idea", "coordinates": [2254, 2097, 2307, 2129], "confidence": 0.846, "entities": [], "pos": [["idea", "NOUN"]]}, {"text": "world", "coordinates": [1319, 2111, 1378, 2135], "confidence": 0.829, "entities": [], "pos": [["world", "NOUN"]]}, {"text": "Srdce", "coordinates": [1384, 2112, 1539, 2137], "confidence": 0, "entities": [["Srdce", "PERSON"]], "pos": [["Srdce", "PROPN"]]}, {"text": "Keep", "coordinates": [1582, 2136, 1630, 2164], "confidence": 0.986, "entities": [], "pos": [["Keep", "VERB"]]}, {"text": "up", "coordinates": [1635, 2137, 1663, 2165], "confidence": 0.864, "entities": [], "pos": [["up", "ADV"]]}, {"text": "with", "coordinates": [1667, 2138, 1716, 2168], "confidence": 0.991, "entities": [], "pos": [["with", "ADP"]]}, {"text": "the", "coordinates": [1720, 2140, 1756, 2170], "confidence": 0.993, "entities": [], "pos": [["the", "PRON"]]}, {"text": "tr", "coordinates": [1760, 2141, 1783, 2171], "confidence": 0.991, "entities": [], "pos": [["tr", "VERB"]]}, {"text": "in", "coordinates": [2148, 2129, 2171, 2159], "confidence": 0.968, "entities": [], "pos": [["in", "ADP"]]}, {"text": "smoking!", "coordinates": [2177, 2129, 2285, 2165], "confidence": 0.942, "entities": [], "pos": [["smoking", "NOUN"], ["!", "PUNCT"]]}, {"text": "women", "coordinates": [1318, 2142, 1384, 2165], "confidence": 0.847, "entities": [], "pos": [["women", "NOUN"]]}, {"text": "keep", "coordinates": [1389, 2142, 1433, 2165], "confidence": 0.846, "entities": [], "pos": [["keep", "VERB"]]}, {"text": "asking", "coordinates": [1437, 2142, 1502, 2165], "confidence": 0.71, "entities": [], "pos": [["asking", "VERB"]]}, {"text": "for", "coordinates": [1504, 2143, 1538, 2165], "confidence": 0.749, "entities": [], "pos": [["for", "ADP"]]}, {"text": "Camels", "coordinates": [1315, 2154, 1396, 2185], "confidence": 0.959, "entities": [], "pos": [["Camels", "NOUN"]]}, {"text": "-", "coordinates": [1403, 2160, 1417, 2186], "confidence": 0.931, "entities": [], "pos": [["-", "PUNCT"]]}, {"text": "the", "coordinates": [1432, 2163, 1469, 2189], "confidence": 0.998, "entities": [], "pos": [["the", "PRON"]]}, {"text": "good,", "coordinates": [1476, 2166, 1540, 2194], "confidence": 0.991, "entities": [], "pos": [["good", "ADJ"], [",", "PUNCT"]]}, {"text": "mendous", "coordinates": [1578, 2158, 1667, 2182], "confidence": 0.996, "entities": [], "pos": [["mendous", "ADJ"]]}, {"text": "demand", "coordinates": [1676, 2157, 1755, 2182], "confidence": 0.692, "entities": [], "pos": [["demand", "NOUN"]]}, {"text": "new", "coordinates": [1840, 2142, 1881, 2172], "confidence": 0.64, "entities": [], "pos": [["new", "ADJ"]]}, {"text": "crushproof", "coordinates": [1885, 2145, 2005, 2177], "confidence": 0.963, "entities": [], "pos": [["crushproof", "NOUN"]]}, {"text": "box!", "coordinates": [2011, 2145, 2066, 2177], "confidence": 0.988, "entities": [], "pos": [["box", "PROPN"], ["!", "PUNCT"]]}, {"text": "ous", "coordinates": [1637, 2167, 1667, 2193], "confidence": 0.353, "entities": [], "pos": [["ous", "ADJ"]]}, {"text": "demand", "coordinates": [1674, 2169, 1755, 2201], "confidence": 0.78, "entities": [], "pos": [["demand", "NOUN"]]}, {"text": "For", "coordinates": [1763, 2175, 1800, 2205], "confidence": 0.145, "entities": [], "pos": [["For", "ADP"]]}, {"text": "mild", "coordinates": [1315, 2183, 1362, 2208], "confidence": 0.982, "entities": [], "pos": [["mild", "ADJ"]]}, {"text": "smoke", "coordinates": [1369, 2185, 1436, 2210], "confidence": 0.997, "entities": [], "pos": [["smoke", "VERB"]]}, {"text": "with", "coordinates": [1444, 2186, 1489, 2210], "confidence": 0.988, "entities": [], "pos": [["with", "ADP"]]}, {"text": "the", "coordinates": [1499, 2186, 1536, 2210], "confidence": 0.998, "entities": [], "pos": [["the", "PRON"]]}, {"text": "finest", "coordinates": [1313, 2199, 1366, 2225], "confidence": 0.782, "entities": [], "pos": [["finest", "ADJ"]]}, {"text": "taste", "coordinates": [1370, 2201, 1420, 2225], "confidence": 0.997, "entities": [], "pos": [["taste", "NOUN"]]}, {"text": "in", "coordinates": [1425, 2202, 1445, 2225], "confidence": 0.998, "entities": [], "pos": [["in", "ADP"]]}, {"text": "tobecar", "coordinates": [1450, 2201, 1538, 2225], "confidence": 0.01, "entities": [], "pos": [["tobecar", "PROPN"]]}, {"text": "Winston!", "coordinates": [1580, 2184, 1679, 2210], "confidence": 0.963, "entities": [["Winston", "GPE"]], "pos": [["Winston", "PROPN"], ["!", "PUNCT"]]}, {"text": "Full,", "coordinates": [1686, 2186, 1745, 2211], "confidence": 0.671, "entities": [], "pos": [["Full", "ADJ"], [",", "PUNCT"]]}, {"text": "The", "coordinates": [1837, 2177, 1877, 2204], "confidence": 0.998, "entities": [], "pos": [["The", "PRON"]]}, {"text": "radio", "coordinates": [1880, 2178, 1933, 2206], "confidence": 0.996, "entities": [], "pos": [["radio", "NOUN"]]}, {"text": "campaign", "coordinates": [1937, 2180, 2032, 2210], "confidence": 0.606, "entities": [], "pos": [["campaign", "NOUN"]]}, {"text": "of", "coordinates": [2038, 2183, 2059, 2212], "confidence": 0.996, "entities": [], "pos": [["of", "ADP"]]}, {"text": "Get", "coordinates": [2101, 2170, 2139, 2194], "confidence": 0.998, "entities": [], "pos": [["Get", "VERB"]]}, {"text": "behind", "coordinates": [2143, 2170, 2213, 2196], "confidence": 0.994, "entities": [], "pos": [["behind", "ADV"]]}, {"text": "this", "coordinates": [2220, 2171, 2262, 2200], "confidence": 0.991, "entities": [], "pos": [["this", "PRON"]]}, {"text": "gr", "coordinates": [2266, 2174, 2289, 2203], "confidence": 0.847, "entities": [], "pos": [["gr", "VERB"]]}, {"text": "flavor", "coordinates": [1574, 2198, 1642, 2224], "confidence": 0.991, "entities": [], "pos": [["flavor", "NOUN"]]}, {"text": "has", "coordinates": [1645, 2201, 1685, 2227], "confidence": 0.958, "entities": [], "pos": [["has", "VERB"]]}, {"text": "made", "coordinates": [1689, 2204, 1746, 2229], "confidence": 0.869, "entities": [], "pos": [["made", "VERB"]]}, {"text": "this", "coordinates": [1750, 2207, 1795, 2231], "confidence": 0.982, "entities": [], "pos": [["this", "PRON"]]}, {"text": "king-size", "coordinates": [1572, 2225, 1658, 2252], "confidence": 0.968, "entities": [], "pos": [["king", "NOUN"], ["-", "PUNCT"], ["size", "NOUN"]]}, {"text": "winner", "coordinates": [1660, 2229, 1728, 2252], "confidence": 0.944, "entities": [], "pos": [["winner", "NOUN"]]}, {"text": "Amer-", "coordinates": [1731, 2231, 1800, 2252], "confidence": 0.941, "entities": [], "pos": [["Amer-", "PROPN"]]}, {"text": "the", "coordinates": [1834, 2207, 1878, 2234], "confidence": 0.305, "entities": [], "pos": [["the", "PRON"]]}, {"text": "year", "coordinates": [1880, 2207, 1937, 2234], "confidence": 0.844, "entities": [], "pos": [["year", "NOUN"]]}, {"text": "is", "coordinates": [1940, 2208, 1967, 2235], "confidence": 0.998, "entities": [], "pos": [["is", "AUX"]]}, {"text": "making", "coordinates": [1971, 2208, 2057, 2239], "confidence": 0.991, "entities": [], "pos": [["making", "VERB"]]}, {"text": "aew", "coordinates": [2100, 2200, 2139, 2222], "confidence": 0.118, "entities": [["aew", "ORG"]], "pos": [["aew", "PROPN"]]}, {"text": "menthol-fresh", "coordinates": [2146, 2200, 2287, 2227], "confidence": 0.766, "entities": [], "pos": [["menthol", "NOUN"], ["-", "PUNCT"], ["fresh", "ADJ"]]}, {"text": "al-", "coordinates": [2292, 2202, 2318, 2229], "confidence": 0.165, "entities": [], "pos": [["al-", "X"]]}, {"text": "Cavalier", "coordinates": [1831, 2221, 1916, 2252], "confidence": 0.991, "entities": [["Cavalier", "ORG"]], "pos": [["Cavalier", "ADJ"]]}, {"text": "the", "coordinates": [1918, 2227, 1952, 2253], "confidence": 0.998, "entities": [], "pos": [["the", "PRON"]]}, {"text": "talk", "coordinates": [1955, 2228, 1995, 2253], "confidence": 0.933, "entities": [], "pos": [["talk", "VERB"]]}, {"text": "of", "coordinates": [1999, 2227, 2018, 2253], "confidence": 0.998, "entities": [], "pos": [["of", "ADP"]]}, {"text": "the", "coordinates": [2023, 2225, 2059, 2252], "confidence": 0.994, "entities": [], "pos": [["the", "PRON"]]}, {"text": "ter", "coordinates": [2099, 2216, 2131, 2236], "confidence": 0.995, "entities": [], "pos": [["ter", "NOUN"]]}, {"text": "smoke", "coordinates": [2137, 2216, 2203, 2237], "confidence": 0.971, "entities": [], "pos": [["smoke", "VERB"]]}, {"text": "that's", "coordinates": [2211, 2215, 2272, 2239], "confidence": 0.942, "entities": [], "pos": [["that", "PRON"], ["'s", "AUX"]]}, {"text": "rich", "coordinates": [2278, 2215, 2319, 2240], "confidence": 0.939, "entities": [], "pos": [["rich", "ADJ"]]}, {"text": "ica's", "coordinates": [1576, 2241, 1619, 2263], "confidence": 0.644, "entities": [], "pos": [["ica", "PROPN"], ["'s", "PART"]]}, {"text": "best-selling", "coordinates": [1622, 2242, 1732, 2265], "confidence": 0.611, "entities": [], "pos": [["best", "ADV"], ["-", "PUNCT"], ["selling", "VERB"]]}, {"text": "beef", "coordinates": [1742, 2245, 1787, 2266], "confidence": 0.004, "entities": [], "pos": [["beef", "NOUN"]]}, {"text": "country", "coordinates": [1834, 2239, 1910, 2267], "confidence": 0.996, "entities": [], "pos": [["country", "NOUN"]]}, {"text": ".", "coordinates": [1913, 2242, 1929, 2266], "confidence": 0.766, "entities": [], "pos": [[".", "PUNCT"]]}, {"text": "Roger", "coordinates": [1932, 2242, 1997, 2267], "confidence": 0.978, "entities": [["Roger", "PERSON"]], "pos": [["Roger", "PROPN"]]}, {"text": "Baus.", "coordinates": [2001, 2244, 2060, 2268], "confidence": 0.43, "entities": [["Baus", "PERSON"]], "pos": [["Baus", "PROPN"], [".", "PUNCT"]]}, {"text": "in", "coordinates": [2099, 2240, 2118, 2262], "confidence": 0.679, "entities": [], "pos": [["in", "ADP"]]}, {"text": "favor,", "coordinates": [2121, 2241, 2185, 2265], "confidence": 0.449, "entities": [], "pos": [["favor", "NOUN"], [",", "PUNCT"]]}, {"text": "too:", "coordinates": [2189, 2244, 2230, 2266], "confidence": 0.676, "entities": [], "pos": [["too", "ADV"], [":", "PUNCT"]]}, {"text": "Salem", "coordinates": [2234, 2245, 2289, 2267], "confidence": 0.991, "entities": [["Salem", "GPE"]], "pos": [["Salem", "NOUN"]]}, {"text": "is", "coordinates": [2299, 2246, 2319, 2267], "confidence": 0.908, "entities": [], "pos": [["is", "AUX"]]}, {"text": "soaring", "coordinates": [2097, 2256, 2171, 2278], "confidence": 0.602, "entities": [], "pos": [["soaring", "VERB"]]}, {"text": "in", "coordinates": [2175, 2256, 2196, 2277], "confidence": 0.017, "entities": [], "pos": [["in", "ADP"]]}, {"text": "Sto", "coordinates": [1320, 2282, 1346, 2306], "confidence": 0.095, "entities": [], "pos": [["Sto", "PROPN"]]}, {"text": "Supply", "coordinates": [1349, 2283, 1403, 2307], "confidence": 0.719, "entities": [], "pos": [["Supply", "NOUN"]]}, {"text": "Bulletin", "coordinates": [1406, 2286, 1466, 2310], "confidence": 0.559, "entities": [], "pos": [["Bulletin", "NOUN"]]}, {"text": "tasting", "coordinates": [1572, 2272, 1646, 2293], "confidence": 0.896, "entities": [], "pos": [["tasting", "VERB"]]}, {"text": "filter", "coordinates": [1653, 2272, 1711, 2293], "confidence": 0.997, "entities": [], "pos": [["filter", "VERB"]]}, {"text": "smoke.", "coordinates": [1715, 2272, 1795, 2294], "confidence": 0.962, "entities": [], "pos": [["smoke", "NOUN"], [".", "PUNCT"]]}, {"text": "Winston", "coordinates": [1582, 2285, 1655, 2309], "confidence": 0.994, "entities": [["Winston", "GPE"]], "pos": [["Winston", "PROPN"]]}, {"text": "tastes", "coordinates": [1659, 2288, 1722, 2311], "confidence": 0.91, "entities": [], "pos": [["tastes", "VERB"]]}, {"text": "good-", "coordinates": [1725, 2291, 1787, 2315], "confidence": 0.772, "entities": [], "pos": [["good-", "X"]]}, {"text": "Won't", "coordinates": [1846, 2273, 1901, 2296], "confidence": 0.16, "entities": [], "pos": [["Wo", "AUX"], ["n't", "PART"]]}, {"text": "forget", "coordinates": [1903, 2272, 1969, 2295], "confidence": 0.994, "entities": [], "pos": [["forget", "VERB"]]}, {"text": "to", "coordinates": [1971, 2272, 1995, 2294], "confidence": 0.998, "entities": [], "pos": [["to", "PART"]]}, {"text": "stock", "coordinates": [1998, 2272, 2054, 2294], "confidence": 0.995, "entities": [], "pos": [["stock", "NOUN"]]}, {"text": "and", "coordinates": [1836, 2281, 1874, 2305], "confidence": 0.998, "entities": [], "pos": [["and", "CCONJ"]]}, {"text": "feature", "coordinates": [1887, 2285, 1981, 2309], "confidence": 0.897, "entities": [], "pos": [["feature", "NOUN"]]}, {"text": "fit.", "coordinates": [1992, 2289, 2056, 2309], "confidence": 0.017, "entities": [], "pos": [["fit", "ADJ"], [".", "PUNCT"]]}, {"text": "got", "coordinates": [2093, 2286, 2129, 2308], "confidence": 0.082, "entities": [], "pos": [["got", "VERB"]]}, {"text": "this", "coordinates": [2131, 2285, 2175, 2306], "confidence": 0.978, "entities": [], "pos": [["this", "PRON"]]}, {"text": "most", "coordinates": [2185, 2285, 2230, 2305], "confidence": 0.98, "entities": [], "pos": [["most", "ADV"]]}, {"text": "refresh-", "coordinates": [2236, 2285, 2319, 2308], "confidence": 0.927, "entities": [], "pos": [["refresh-", "X"]]}, {"text": "No.", "coordinates": [1335, 2301, 1365, 2323], "confidence": 0.502, "entities": [], "pos": [["No", "INTJ"], [".", "PUNCT"]]}, {"text": "10", "coordinates": [1367, 2302, 1392, 2324], "confidence": 0.747, "entities": [["10", "CARDINAL"]], "pos": [["10", "NUM"]]}, {"text": "500-55", "coordinates": [1394, 2303, 1452, 2325], "confidence": 0.703, "entities": [["500-55", "CARDINAL"]], "pos": [["500", "NUM"], ["-", "SYM"], ["55", "NUM"]]}, {"text": "imiston", "coordinates": [1576, 2297, 1653, 2320], "confidence": 0.101, "entities": [["imiston", "GPE"]], "pos": [["imiston", "PROPN"]]}, {"text": "tastes", "coordinates": [1659, 2299, 1719, 2321], "confidence": 0.694, "entities": [], "pos": [["tastes", "VERB"]]}, {"text": "g", "coordinates": [1724, 2299, 1734, 2320], "confidence": 0.068, "entities": [], "pos": [["g", "ADP"]]}, {"text": "moving", "coordinates": [1833, 2297, 1904, 2328], "confidence": 0.262, "entities": [], "pos": [["moving", "VERB"]]}, {"text": "Cavalier!\"", "coordinates": [1910, 2307, 2016, 2333], "confidence": 0.852, "entities": [["Cavalier", "ORG"]], "pos": [["Cavalier", "ADJ"], ["!", "PUNCT"], ["\"", "PUNCT"]]}, {"text": "ing", "coordinates": [2092, 2299, 2124, 2320], "confidence": 0.993, "entities": [], "pos": [["ing", "VERB"]]}, {"text": "cigarette", "coordinates": [2127, 2301, 2213, 2323], "confidence": 0.991, "entities": [], "pos": [["cigarette", "PROPN"]]}, {"text": "was", "coordinates": [2218, 2303, 2254, 2323], "confidence": 0.967, "entities": [], "pos": [["was", "AUX"]]}, {"text": "intro-", "coordinates": [2257, 2303, 2319, 2324], "confidence": 0.847, "entities": [], "pos": [["intro-", "ADP"]]}, {"text": "like", "coordinates": [1567, 2308, 1604, 2333], "confidence": 0.796, "entities": [], "pos": [["like", "INTJ"]]}, {"text": "a", "coordinates": [1608, 2311, 1619, 2334], "confidence": 0.089, "entities": [], "pos": [["a", "PRON"]]}, {"text": "cigarette", "coordinates": [1623, 2312, 1708, 2339], "confidence": 0.854, "entities": [], "pos": [["cigarette", "PROPN"]]}, {"text": "should!", "coordinates": [1713, 2317, 1789, 2342], "confidence": 0.873, "entities": [], "pos": [["should", "AUX"], ["!", "PUNCT"]]}, {"text": "ed", "coordinates": [2128, 2326, 2150, 2350], "confidence": 0.853, "entities": [], "pos": [["ed", "PROPN"]]}, {"text": "just", "coordinates": [2154, 2326, 2193, 2349], "confidence": 0.987, "entities": [], "pos": [["just", "ADV"]]}, {"text": "last", "coordinates": [2197, 2326, 2238, 2350], "confidence": 0.981, "entities": [], "pos": [["last", "ADJ"]]}, {"text": "year!", "coordinates": [2241, 2327, 2302, 2354], "confidence": 0.991, "entities": [], "pos": [["year", "NOUN"], ["!", "PUNCT"]]}, {"text": "R.", "coordinates": [1302, 2347, 1335, 2384], "confidence": 0.997, "entities": [["R.", "NORP"]], "pos": [["R.", "PROPN"]]}, {"text": "J.", "coordinates": [1341, 2349, 1370, 2386], "confidence": 0.997, "entities": [], "pos": [["J.", "PROPN"]]}, {"text": "REYNOLDS", "coordinates": [1376, 2351, 1559, 2393], "confidence": 0.962, "entities": [["REYNOLDS", "ORG"]], "pos": [["REYNOLDS", "PROPN"]]}, {"text": "TOBACCO", "coordinates": [1574, 2361, 1731, 2401], "confidence": 0.964, "entities": [], "pos": [["TOBACCO", "NOUN"]]}, {"text": "COMPANY", "coordinates": [1743, 2370, 1911, 2409], "confidence": 0.996, "entities": [], "pos": [["COMPANY", "PROPN"]]}, {"text": ".", "coordinates": [1917, 2378, 1929, 2410], "confidence": 0.609, "entities": [], "pos": [[".", "PUNCT"]]}, {"text": "WINSTON-SALEM,", "coordinates": [1934, 2379, 2238, 2427], "confidence": 0.918, "entities": [["WINSTON-SALEM", "GPE"]], "pos": [["WINSTON", "PROPN"], ["-", "PUNCT"], ["SALEM", "PROPN"], [",", "PUNCT"]]}, {"text": "N.", "coordinates": [2243, 2394, 2279, 2429], "confidence": 0.994, "entities": [], "pos": [["N.", "VERB"]]}, {"text": "C.", "coordinates": [2284, 2395, 2326, 2432], "confidence": 0.997, "entities": [], "pos": [["C.", "PROPN"]]}, {"text": "This", "coordinates": [1689, 2437, 1722, 2459], "confidence": 0.886, "entities": [], "pos": [["This", "PRON"]]}, {"text": "advertisement", "coordinates": [1725, 2437, 1827, 2463], "confidence": 0.451, "entities": [], "pos": [["advertisement", "NOUN"]]}, {"text": "prepared", "coordinates": [1831, 2439, 1900, 2465], "confidence": 0.51, "entities": [], "pos": [["prepared", "VERB"]]}, {"text": "WILLIAM", "coordinates": [1689, 2452, 1771, 2480], "confidence": 0.969, "entities": [["WILLIAM", "ORG"]], "pos": [["WILLIAM", "PROPN"]]}, {"text": "ESTY", "coordinates": [1776, 2456, 1823, 2481], "confidence": 0.651, "entities": [["ESTY", "ORG"]], "pos": [["ESTY", "PROPN"]]}, {"text": "COMPANY", "coordinates": [1828, 2458, 1919, 2482], "confidence": 0.616, "entities": [], "pos": [["COMPANY", "PROPN"]]}, {"text": "ILLIAM", "coordinates": [1710, 2465, 1772, 2489], "confidence": 0.086, "entities": [["ILLIAM", "ORG"]], "pos": [["ILLIAM", "NOUN"]]}, {"text": "ESTY", "coordinates": [1777, 2469, 1826, 2491], "confidence": 0.487, "entities": [["ESTY", "ORG"]], "pos": [["ESTY", "PROPN"]]}, {"text": "COM", "coordinates": [1829, 2471, 1868, 2491], "confidence": 0.652, "entities": [], "pos": [["COM", "NOUN"]]}, {"text": "INCORPORATED", "coordinates": [1741, 2483, 1863, 2511], "confidence": 0.62, "entities": [], "pos": [["INCORPORATED", "VERB"]]}, {"text": "..", "coordinates": [1662, 2546, 1704, 2576], "confidence": 0.093, "entities": [], "pos": [["..", "PUNCT"]]}, {"text": "Ad", "coordinates": [1731, 2542, 1758, 2569], "confidence": 0.997, "entities": [], "pos": [["Ad", "NOUN"]]}, {"text": "No.1-8719A", "coordinates": [1763, 2542, 1867, 2571], "confidence": 0.702, "entities": [["No.1-8719A", "PRODUCT"]], "pos": [["No.1", "NOUN"], ["-", "PUNCT"], ["8719A", "PROPN"]]}, {"text": "This", "coordinates": [1668, 2566, 1705, 2591], "confidence": 0.987, "entities": [], "pos": [["This", "PRON"]]}, {"text": "advertisement", "coordinates": [1708, 2567, 1830, 2593], "confidence": 0.47, "entities": [], "pos": [["advertisement", "NOUN"]]}, {"text": "appears", "coordinates": [1833, 2570, 1899, 2596], "confidence": 0.883, "entities": [], "pos": [["appears", "VERB"]]}, {"text": "in:", "coordinates": [1903, 2574, 1936, 2598], "confidence": 0.791, "entities": [], "pos": [["in", "ADP"], [":", "PUNCT"]]}, {"text": "50259", "coordinates": [2388, 2588, 2423, 2662], "confidence": 0.793, "entities": [["50259", "CARDINAL"]], "pos": [["50259", "NUM"]]}, {"text": "9068", "coordinates": [2386, 2671, 2417, 2733], "confidence": 0.905, "entities": [["9068", "DATE"]], "pos": [["9068", "NUM"]]}, {"text": "1997", "coordinates": [1601, 2591, 1643, 2617], "confidence": 0.749, "entities": [["1997", "DATE"]], "pos": [["1997", "NUM"]]}, {"text": "Souvenir", "coordinates": [1647, 2591, 1727, 2616], "confidence": 0.841, "entities": [], "pos": [["Souvenir", "PROPN"]]}, {"text": "Program", "coordinates": [1732, 2592, 1804, 2619], "confidence": 0.93, "entities": [], "pos": [["Program", "NOUN"]]}, {"text": "of", "coordinates": [1810, 2595, 1824, 2620], "confidence": 0.996, "entities": [], "pos": [["of", "ADP"]]}, {"text": "the", "coordinates": [1829, 2596, 1863, 2622], "confidence": 0.982, "entities": [], "pos": [["the", "PRON"]]}, {"text": "Quartermaster", "coordinates": [1868, 2599, 1993, 2636], "confidence": 0.661, "entities": [], "pos": [["Quartermaster", "PROPN"]]}, {"text": "Association", "coordinates": [1557, 2609, 1653, 2638], "confidence": 0.675, "entities": [], "pos": [["Association", "PROPN"]]}, {"text": "Nacional", "coordinates": [1657, 2613, 1736, 2641], "confidence": 0.684, "entities": [], "pos": [["Nacional", "ADJ"]]}, {"text": "Convention,", "coordinates": [1739, 2617, 1847, 2646], "confidence": 0.559, "entities": [], "pos": [["Convention", "PROPN"], [",", "PUNCT"]]}, {"text": "October", "coordinates": [1850, 2622, 1921, 2651], "confidence": 0.848, "entities": [["October", "DATE"]], "pos": [["October", "PROPN"]]}, {"text": "3", "coordinates": [1924, 2626, 1935, 2652], "confidence": 0.996, "entities": [["3", "CARDINAL"]], "pos": [["3", "NUM"]]}, {"text": "and", "coordinates": [1937, 2627, 1972, 2655], "confidence": 0.81, "entities": [], "pos": [["and", "CCONJ"]]}, {"text": "4,", "coordinates": [1974, 2629, 1992, 2656], "confidence": 0.844, "entities": [["4", "CARDINAL"]], "pos": [["4", "X"], [",", "PUNCT"]]}, {"text": "1957", "coordinates": [1994, 2630, 2042, 2661], "confidence": 0.983, "entities": [["1957", "DATE"]], "pos": [["1957", "NUM"]]}, {"text": "...", "coordinates": [2356, 2632, 2380, 2673], "confidence": 0.888, "entities": [], "pos": [["...", "PUNCT"]]}]