[{"text": "RHC", "coordinates": [306, 114, 404, 172], "confidence": 0.989, "entities": [["RHC", "ORG"]], "pos": [["RHC", "PROPN"]]}, {"text": "JLM", "coordinates": [1376, 81, 1505, 155], "confidence": 0.62, "entities": [["JLM", "PERSON"]], "pos": [["JLM", "PROPN"]]}, {"text": "AC:", "coordinates": [203, 143, 291, 213], "confidence": 0.671, "entities": [], "pos": [["AC", "PROPN"], [":", "PUNCT"]]}, {"text": "DPJ", "coordinates": [323, 173, 401, 220], "confidence": 0.961, "entities": [["DPJ", "ORG"]], "pos": [["DPJ", "PROPN"]]}, {"text": "RUR", "coordinates": [652, 166, 817, 258], "confidence": 0.811, "entities": [["RUR", "ORG"]], "pos": [["RUR", "VERB"]]}, {"text": "March", "coordinates": [1014, 216, 1120, 254], "confidence": 0.998, "entities": [["March", "DATE"]], "pos": [["March", "PROPN"]]}, {"text": "17,", "coordinates": [1136, 215, 1205, 253], "confidence": 0.998, "entities": [["17", "CARDINAL"]], "pos": [["17", "NUM"], [",", "PUNCT"]]}, {"text": "1978", "coordinates": [1216, 214, 1301, 253], "confidence": 0.989, "entities": [["1978", "DATE"]], "pos": [["1978", "NUM"]]}, {"text": "SECRET", "coordinates": [628, 264, 855, 358], "confidence": 0.844, "entities": [], "pos": [["SECRET", "PROPN"]]}, {"text": "Mr.", "coordinates": [238, 376, 302, 414], "confidence": 0.9, "entities": [], "pos": [["Mr.", "PROPN"]]}, {"text": "R.", "coordinates": [314, 375, 360, 420], "confidence": 0.955, "entities": [["R.", "NORP"]], "pos": [["R.", "PROPN"]]}, {"text": "A.", "coordinates": [372, 374, 418, 426], "confidence": 0.699, "entities": [], "pos": [["A.", "PROPN"]]}, {"text": "Karel0,", "coordinates": [430, 370, 593, 437], "confidence": 0.09, "entities": [], "pos": [["Karel0", "PROPN"], [",", "PUNCT"]]}, {"text": "259", "coordinates": [603, 364, 729, 439], "confidence": 0.848, "entities": [["259", "CARDINAL"]], "pos": [["259", "NUM"]]}, {"text": "By", "coordinates": [760, 359, 837, 439], "confidence": 0.982, "entities": [], "pos": [["By", "ADP"]]}, {"text": "Ame", "coordinates": [867, 351, 978, 437], "confidence": 0.893, "entities": [], "pos": [["Ame", "NOUN"]]}, {"text": "Re:", "coordinates": [304, 482, 371, 518], "confidence": 0.991, "entities": [], "pos": [["Re", "NOUN"], [":", "PUNCT"]]}, {"text": "WINSTON", "coordinates": [403, 481, 545, 518], "confidence": 0.996, "entities": [["WINSTON", "GPE"]], "pos": [["WINSTON", "PROPN"]]}, {"text": "100's", "coordinates": [565, 480, 668, 518], "confidence": 0.87, "entities": [["100", "CARDINAL"]], "pos": [["100", "NUM"], ["'s", "PART"]]}, {"text": "\"X\",", "coordinates": [686, 480, 772, 518], "confidence": 0.921, "entities": [], "pos": [["\"", "PUNCT"], ["X", "NOUN"], ["\"", "PUNCT"], [",", "PUNCT"]]}, {"text": "16", "coordinates": [784, 480, 829, 518], "confidence": 0.997, "entities": [["16", "CARDINAL"]], "pos": [["16", "NUM"]]}, {"text": "mg", "coordinates": [841, 479, 890, 518], "confidence": 0.944, "entities": [], "pos": [["mg", "PROPN"]]}, {"text": "Tar", "coordinates": [905, 479, 967, 517], "confidence": 0.998, "entities": [], "pos": [["Tar", "NOUN"]]}, {"text": "Unannounced", "coordinates": [984, 478, 1206, 517], "confidence": 0.993, "entities": [], "pos": [["Unannounced", "ADJ"]]}, {"text": "Shipment", "coordinates": [1222, 478, 1388, 517], "confidence": 0.996, "entities": [], "pos": [["Shipment", "PROPN"]]}, {"text": "Test", "coordinates": [1404, 477, 1487, 516], "confidence": 0.989, "entities": [], "pos": [["Test", "NOUN"]]}, {"text": "The", "coordinates": [247, 591, 306, 627], "confidence": 0.998, "entities": [], "pos": [["The", "PRON"]]}, {"text": "purpose", "coordinates": [322, 588, 465, 627], "confidence": 0.996, "entities": [], "pos": [["purpose", "NOUN"]]}, {"text": "of", "coordinates": [484, 587, 526, 625], "confidence": 0.998, "entities": [], "pos": [["of", "ADP"]]}, {"text": "this", "coordinates": [545, 585, 626, 625], "confidence": 0.989, "entities": [], "pos": [["this", "PRON"]]}, {"text": "document", "coordinates": [643, 584, 807, 623], "confidence": 0.995, "entities": [], "pos": [["document", "NOUN"]]}, {"text": "is", "coordinates": [826, 583, 865, 622], "confidence": 0.995, "entities": [], "pos": [["is", "AUX"]]}, {"text": "to", "coordinates": [887, 583, 926, 621], "confidence": 0.998, "entities": [], "pos": [["to", "PART"]]}, {"text": "outline", "coordinates": [943, 582, 1085, 621], "confidence": 0.995, "entities": [], "pos": [["outline", "NOUN"]]}, {"text": "the", "coordinates": [1105, 582, 1165, 619], "confidence": 0.998, "entities": [], "pos": [["the", "PRON"]]}, {"text": "current", "coordinates": [1184, 582, 1327, 618], "confidence": 0.995, "entities": [], "pos": [["current", "ADJ"]]}, {"text": "status", "coordinates": [1343, 583, 1467, 617], "confidence": 0.997, "entities": [], "pos": [["status", "NOUN"]]}, {"text": "and", "coordinates": [1486, 583, 1547, 615], "confidence": 0.994, "entities": [], "pos": [["and", "CCONJ"]]}, {"text": "proposed", "coordinates": [249, 626, 405, 660], "confidence": 0.992, "entities": [], "pos": [["proposed", "VERB"]]}, {"text": "timetable", "coordinates": [426, 624, 605, 660], "confidence": 0.991, "entities": [], "pos": [["timetable", "NOUN"]]}, {"text": "for", "coordinates": [626, 622, 685, 658], "confidence": 0.998, "entities": [], "pos": [["for", "ADP"]]}, {"text": "unannounced", "coordinates": [706, 620, 924, 658], "confidence": 0.993, "entities": [], "pos": [["unannounced", "ADJ"]]}, {"text": "shipment", "coordinates": [944, 618, 1106, 657], "confidence": 0.996, "entities": [], "pos": [["shipment", "NOUN"]]}, {"text": "test", "coordinates": [1124, 618, 1204, 655], "confidence": 0.989, "entities": [], "pos": [["test", "NOUN"]]}, {"text": "of", "coordinates": [1222, 617, 1266, 654], "confidence": 0.998, "entities": [], "pos": [["of", "ADP"]]}, {"text": "the", "coordinates": [1283, 618, 1346, 653], "confidence": 0.998, "entities": [], "pos": [["the", "PRON"]]}, {"text": "WINSTON", "coordinates": [1361, 617, 1505, 651], "confidence": 0.996, "entities": [["WINSTON", "GPE"]], "pos": [["WINSTON", "PROPN"]]}, {"text": "100's", "coordinates": [250, 656, 347, 696], "confidence": 0.951, "entities": [["100", "CARDINAL"]], "pos": [["100", "NUM"], ["'s", "PART"]]}, {"text": "16", "coordinates": [366, 659, 408, 696], "confidence": 0.998, "entities": [["16", "CARDINAL"]], "pos": [["16", "NUM"]]}, {"text": "mg", "coordinates": [424, 660, 468, 696], "confidence": 0.993, "entities": [], "pos": [["mg", "PROPN"]]}, {"text": "product.", "coordinates": [485, 660, 647, 695], "confidence": 0.995, "entities": [], "pos": [["product", "NOUN"], [".", "PUNCT"]]}, {"text": "Background", "coordinates": [247, 765, 448, 800], "confidence": 0.995, "entities": [["Background", "GPE"]], "pos": [["Background", "NOUN"]]}, {"text": "The", "coordinates": [250, 836, 308, 869], "confidence": 0.998, "entities": [], "pos": [["The", "PRON"]]}, {"text": "WINSTON", "coordinates": [326, 834, 467, 868], "confidence": 0.996, "entities": [["WINSTON", "GPE"]], "pos": [["WINSTON", "PROPN"]]}, {"text": "100's", "coordinates": [487, 832, 587, 867], "confidence": 0.994, "entities": [["100", "CARDINAL"]], "pos": [["100", "NUM"], ["'s", "PART"]]}, {"text": "Improved", "coordinates": [607, 831, 768, 867], "confidence": 0.994, "entities": [], "pos": [["Improved", "VERB"]]}, {"text": "Product", "coordinates": [786, 829, 929, 864], "confidence": 0.997, "entities": [], "pos": [["Product", "NOUN"]]}, {"text": "program", "coordinates": [945, 828, 1086, 864], "confidence": 0.995, "entities": [], "pos": [["program", "NOUN"]]}, {"text": "was", "coordinates": [1106, 828, 1168, 863], "confidence": 0.998, "entities": [], "pos": [["was", "AUX"]]}, {"text": "initiated", "coordinates": [1188, 826, 1367, 861], "confidence": 0.993, "entities": [], "pos": [["initiated", "VERB"]]}, {"text": "in", "coordinates": [1390, 826, 1426, 861], "confidence": 0.998, "entities": [], "pos": [["in", "ADP"]]}, {"text": "February,", "coordinates": [1446, 825, 1630, 860], "confidence": 0.993, "entities": [["February", "DATE"]], "pos": [["February", "PROPN"], [",", "PUNCT"]]}, {"text": "1977,", "coordinates": [250, 870, 350, 905], "confidence": 0.994, "entities": [["1977", "DATE"]], "pos": [["1977", "NUM"], [",", "PUNCT"]]}, {"text": "when", "coordinates": [366, 869, 448, 904], "confidence": 0.988, "entities": [], "pos": [["when", "SCONJ"]]}, {"text": "NFO", "coordinates": [466, 868, 526, 903], "confidence": 0.994, "entities": [["NFO", "ORG"]], "pos": [["NFO", "PROPN"]]}, {"text": "results", "coordinates": [547, 867, 689, 903], "confidence": 0.995, "entities": [], "pos": [["results", "NOUN"]]}, {"text": "determined", "coordinates": [707, 865, 908, 902], "confidence": 0.994, "entities": [], "pos": [["determined", "VERB"]]}, {"text": "that", "coordinates": [928, 865, 1008, 900], "confidence": 0.989, "entities": [], "pos": [["that", "SCONJ"]]}, {"text": "the", "coordinates": [1029, 864, 1089, 899], "confidence": 0.998, "entities": [], "pos": [["the", "PRON"]]}, {"text": "current", "coordinates": [1107, 862, 1250, 898], "confidence": 0.996, "entities": [], "pos": [["current", "ADJ"]]}, {"text": "product", "coordinates": [1265, 862, 1408, 896], "confidence": 0.997, "entities": [], "pos": [["product", "NOUN"]]}, {"text": "was", "coordinates": [1426, 861, 1489, 895], "confidence": 0.998, "entities": [], "pos": [["was", "AUX"]]}, {"text": "less", "coordinates": [1506, 861, 1588, 894], "confidence": 0.991, "entities": [], "pos": [["less", "ADV"]]}, {"text": "preferred", "coordinates": [251, 906, 427, 940], "confidence": 0.993, "entities": [], "pos": [["preferred", "ADJ"]]}, {"text": "to", "coordinates": [449, 905, 487, 939], "confidence": 0.998, "entities": [], "pos": [["to", "PART"]]}, {"text": "Marlboro", "coordinates": [505, 903, 668, 938], "confidence": 0.994, "entities": [["Marlboro", "ORG"]], "pos": [["Marlboro", "PROPN"]]}, {"text": "in", "coordinates": [688, 902, 728, 938], "confidence": 0.998, "entities": [], "pos": [["in", "ADP"]]}, {"text": "blind", "coordinates": [746, 900, 848, 937], "confidence": 0.997, "entities": [], "pos": [["blind", "ADJ"]]}, {"text": "testing.", "coordinates": [869, 899, 1033, 936], "confidence": 0.996, "entities": [], "pos": [["testing", "NOUN"], [".", "PUNCT"]]}, {"text": "Test", "coordinates": [1068, 898, 1149, 935], "confidence": 0.988, "entities": [], "pos": [["Test", "NOUN"]]}, {"text": "results", "coordinates": [1166, 897, 1308, 933], "confidence": 0.996, "entities": [], "pos": [["results", "NOUN"]]}, {"text": "showed", "coordinates": [1327, 896, 1448, 931], "confidence": 0.997, "entities": [], "pos": [["showed", "VERB"]]}, {"text": "that", "coordinates": [1466, 896, 1547, 929], "confidence": 0.989, "entities": [], "pos": [["that", "SCONJ"]]}, {"text": "female", "coordinates": [250, 941, 368, 973], "confidence": 0.994, "entities": [], "pos": [["female", "NOUN"]]}, {"text": "WINSTON", "coordinates": [385, 939, 527, 974], "confidence": 0.997, "entities": [["WINSTON", "GPE"]], "pos": [["WINSTON", "PROPN"]]}, {"text": "100's", "coordinates": [549, 938, 649, 973], "confidence": 0.87, "entities": [["100", "CARDINAL"]], "pos": [["100", "NUM"], ["'s", "PART"]]}, {"text": "smokers", "coordinates": [669, 937, 808, 973], "confidence": 0.996, "entities": [], "pos": [["smokers", "NOUN"]]}, {"text": "and", "coordinates": [828, 936, 888, 972], "confidence": 0.998, "entities": [], "pos": [["and", "CCONJ"]]}, {"text": "all", "coordinates": [908, 935, 968, 970], "confidence": 0.997, "entities": [], "pos": [["all", "PRON"]]}, {"text": "Marlboro", "coordinates": [986, 933, 1148, 970], "confidence": 0.993, "entities": [["Marlboro", "ORG"]], "pos": [["Marlboro", "PROPN"]]}, {"text": "smokers", "coordinates": [1167, 931, 1309, 968], "confidence": 0.996, "entities": [], "pos": [["smokers", "NOUN"]]}, {"text": "preferred", "coordinates": [1327, 930, 1507, 966], "confidence": 0.995, "entities": [], "pos": [["preferred", "ADJ"]]}, {"text": "Marlboro", "coordinates": [247, 974, 409, 1010], "confidence": 0.991, "entities": [["Marlboro", "ORG"]], "pos": [["Marlboro", "PROPN"]]}, {"text": "100's", "coordinates": [430, 974, 530, 1009], "confidence": 0.994, "entities": [["100", "CARDINAL"]], "pos": [["100", "NUM"], ["'s", "PART"]]}, {"text": "over", "coordinates": [548, 973, 630, 1009], "confidence": 0.987, "entities": [], "pos": [["over", "ADV"]]}, {"text": "WINSTON", "coordinates": [646, 971, 790, 1008], "confidence": 0.996, "entities": [["WINSTON", "GPE"]], "pos": [["WINSTON", "PROPN"]]}, {"text": "100's.", "coordinates": [811, 970, 933, 1007], "confidence": 0.991, "entities": [["100", "CARDINAL"]], "pos": [["100", "NUM"], ["'s", "PART"], [".", "PUNCT"]]}, {"text": "The", "coordinates": [970, 969, 1031, 1005], "confidence": 0.998, "entities": [], "pos": [["The", "PRON"]]}, {"text": "primary", "coordinates": [1047, 968, 1191, 1005], "confidence": 0.996, "entities": [], "pos": [["primary", "ADJ"]]}, {"text": "reason", "coordinates": [1209, 967, 1330, 1003], "confidence": 0.997, "entities": [], "pos": [["reason", "NOUN"]]}, {"text": "for", "coordinates": [1350, 967, 1410, 1002], "confidence": 0.998, "entities": [], "pos": [["for", "ADP"]]}, {"text": "WINSTON'S", "coordinates": [1427, 964, 1610, 1000], "confidence": 0.991, "entities": [["WINSTON", "GPE"]], "pos": [["WINSTON", "PROPN"], ["'S", "PART"]]}, {"text": "lack", "coordinates": [251, 1011, 327, 1045], "confidence": 0.991, "entities": [], "pos": [["lack", "NOUN"]]}, {"text": "of", "coordinates": [347, 1010, 393, 1044], "confidence": 0.993, "entities": [], "pos": [["of", "ADP"]]}, {"text": "preference", "coordinates": [406, 1009, 609, 1044], "confidence": 0.995, "entities": [], "pos": [["preference", "NOUN"]]}, {"text": "was", "coordinates": [627, 1007, 693, 1042], "confidence": 0.994, "entities": [], "pos": [["was", "AUX"]]}, {"text": "its", "coordinates": [711, 1007, 769, 1042], "confidence": 0.998, "entities": [], "pos": [["its", "PRON"]]}, {"text": "being", "coordinates": [787, 1006, 889, 1041], "confidence": 0.997, "entities": [], "pos": [["being", "AUX"]]}, {"text": "perceived", "coordinates": [909, 1003, 1090, 1040], "confidence": 0.995, "entities": [], "pos": [["perceived", "VERB"]]}, {"text": "\"too", "coordinates": [1112, 1002, 1191, 1038], "confidence": 0.958, "entities": [], "pos": [["\"", "PUNCT"], ["too", "ADV"]]}, {"text": "strong/harsh\"", "coordinates": [1209, 999, 1471, 1037], "confidence": 0.991, "entities": [], "pos": [["strong", "ADJ"], ["/", "SYM"], ["harsh", "ADJ"], ["\"", "PUNCT"]]}, {"text": "\"less", "coordinates": [1492, 998, 1588, 1033], "confidence": 0.945, "entities": [], "pos": [["\"", "PUNCT"], ["less", "ADV"]]}, {"text": "smooth/mild\"", "coordinates": [251, 1042, 492, 1079], "confidence": 0.941, "entities": [], "pos": [["smooth", "ADJ"], ["/", "SYM"], ["mild", "ADJ"], ["\"", "PUNCT"]]}, {"text": "relative", "coordinates": [510, 1041, 670, 1076], "confidence": 0.995, "entities": [], "pos": [["relative", "ADJ"]]}, {"text": "to", "coordinates": [691, 1040, 730, 1076], "confidence": 0.998, "entities": [], "pos": [["to", "PART"]]}, {"text": "Marlboro.", "coordinates": [746, 1040, 926, 1075], "confidence": 0.968, "entities": [["Marlboro", "ORG"]], "pos": [["Marlboro", "PROPN"], [".", "PUNCT"]]}, {"text": "Accordingly,", "coordinates": [252, 1115, 495, 1153], "confidence": 0.991, "entities": [], "pos": [["Accordingly", "ADV"], [",", "PUNCT"]]}, {"text": "three", "coordinates": [512, 1114, 611, 1150], "confidence": 0.998, "entities": [["three", "CARDINAL"]], "pos": [["three", "NUM"]]}, {"text": "lowered-tar", "coordinates": [629, 1111, 851, 1148], "confidence": 0.993, "entities": [], "pos": [["lowered", "VERB"], ["-", "PUNCT"], ["tar", "NOUN"]]}, {"text": "blends", "coordinates": [867, 1111, 991, 1146], "confidence": 0.996, "entities": [], "pos": [["blends", "NOUN"]]}, {"text": "were", "coordinates": [1007, 1109, 1090, 1146], "confidence": 0.987, "entities": [], "pos": [["were", "AUX"]]}, {"text": "developed", "coordinates": [1109, 1108, 1291, 1145], "confidence": 0.995, "entities": [], "pos": [["developed", "VERB"]]}, {"text": "which", "coordinates": [1307, 1107, 1409, 1142], "confidence": 0.998, "entities": [], "pos": [["which", "PRON"]]}, {"text": "were", "coordinates": [1427, 1106, 1510, 1142], "confidence": 0.988, "entities": [], "pos": [["were", "AUX"]]}, {"text": "judged", "coordinates": [252, 1152, 370, 1186], "confidence": 0.993, "entities": [], "pos": [["judged", "VERB"]]}, {"text": "to", "coordinates": [391, 1152, 429, 1186], "confidence": 0.998, "entities": [], "pos": [["to", "PART"]]}, {"text": "be", "coordinates": [448, 1151, 491, 1185], "confidence": 0.998, "entities": [], "pos": [["be", "AUX"]]}, {"text": "milder", "coordinates": [508, 1150, 631, 1184], "confidence": 0.996, "entities": [], "pos": [["milder", "NOUN"]]}, {"text": "than", "coordinates": [651, 1150, 730, 1184], "confidence": 0.988, "entities": [], "pos": [["than", "ADP"]]}, {"text": "current", "coordinates": [752, 1149, 893, 1183], "confidence": 0.996, "entities": [], "pos": [["current", "ADJ"]]}, {"text": "WINSTON", "coordinates": [911, 1147, 1051, 1182], "confidence": 0.995, "entities": [["WINSTON", "GPE"]], "pos": [["WINSTON", "PROPN"]]}, {"text": "100's.", "coordinates": [1071, 1145, 1194, 1181], "confidence": 0.991, "entities": [["100", "CARDINAL"]], "pos": [["100", "NUM"], ["'s", "PART"], [".", "PUNCT"]]}, {"text": "It", "coordinates": [1231, 1145, 1271, 1179], "confidence": 0.998, "entities": [], "pos": [["It", "PRON"]]}, {"text": "was", "coordinates": [1288, 1144, 1350, 1178], "confidence": 0.998, "entities": [], "pos": [["was", "AUX"]]}, {"text": "intended", "coordinates": [1372, 1142, 1531, 1177], "confidence": 0.996, "entities": [], "pos": [["intended", "VERB"]]}, {"text": "that", "coordinates": [255, 1187, 330, 1221], "confidence": 0.992, "entities": [], "pos": [["that", "SCONJ"]]}, {"text": "one", "coordinates": [350, 1187, 410, 1220], "confidence": 0.998, "entities": [["one", "CARDINAL"]], "pos": [["one", "NUM"]]}, {"text": "of", "coordinates": [430, 1186, 471, 1221], "confidence": 0.998, "entities": [], "pos": [["of", "ADP"]]}, {"text": "the", "coordinates": [493, 1186, 551, 1220], "confidence": 0.998, "entities": [], "pos": [["the", "PRON"]]}, {"text": "products", "coordinates": [571, 1185, 731, 1219], "confidence": 0.996, "entities": [], "pos": [["products", "NOUN"]]}, {"text": "would", "coordinates": [750, 1183, 850, 1218], "confidence": 0.998, "entities": [], "pos": [["would", "AUX"]]}, {"text": "be", "coordinates": [869, 1182, 910, 1217], "confidence": 0.998, "entities": [], "pos": [["be", "AUX"]]}, {"text": "introduced", "coordinates": [934, 1181, 1132, 1216], "confidence": 0.995, "entities": [], "pos": [["introduced", "VERB"]]}, {"text": "into", "coordinates": [1152, 1180, 1231, 1214], "confidence": 0.989, "entities": [], "pos": [["into", "ADP"]]}, {"text": "an", "coordinates": [1252, 1180, 1292, 1213], "confidence": 0.998, "entities": [], "pos": [["an", "PRON"]]}, {"text": "\"announced\"", "coordinates": [1312, 1178, 1535, 1212], "confidence": 0.982, "entities": [], "pos": [["\"", "PUNCT"], ["announced", "VERB"], ["\"", "PUNCT"]]}, {"text": "test", "coordinates": [254, 1221, 331, 1255], "confidence": 0.994, "entities": [], "pos": [["test", "NOUN"]]}, {"text": "market", "coordinates": [348, 1220, 472, 1255], "confidence": 0.997, "entities": [], "pos": [["market", "NOUN"]]}, {"text": "if", "coordinates": [492, 1220, 533, 1255], "confidence": 0.998, "entities": [], "pos": [["if", "SCONJ"]]}, {"text": "it", "coordinates": [552, 1220, 593, 1255], "confidence": 0.998, "entities": [], "pos": [["it", "PRON"]]}, {"text": "met", "coordinates": [608, 1220, 672, 1255], "confidence": 0.998, "entities": [], "pos": [["met", "VERB"]]}, {"text": "the", "coordinates": [692, 1219, 752, 1254], "confidence": 0.998, "entities": [], "pos": [["the", "PRON"]]}, {"text": "required", "coordinates": [770, 1218, 932, 1254], "confidence": 0.995, "entities": [], "pos": [["required", "VERB"]]}, {"text": "action", "coordinates": [952, 1217, 1071, 1253], "confidence": 0.997, "entities": [], "pos": [["action", "NOUN"]]}, {"text": "standards,", "coordinates": [1091, 1215, 1295, 1251], "confidence": 0.995, "entities": [], "pos": [["standards", "NOUN"], [",", "PUNCT"]]}, {"text": "which", "coordinates": [1309, 1214, 1410, 1248], "confidence": 0.994, "entities": [], "pos": [["which", "PRON"]]}, {"text": "have", "coordinates": [1428, 1212, 1511, 1246], "confidence": 0.988, "entities": [], "pos": [["have", "VERB"]]}, {"text": "since", "coordinates": [1529, 1211, 1630, 1246], "confidence": 0.994, "entities": [], "pos": [["since", "SCONJ"]]}, {"text": "been", "coordinates": [251, 1255, 331, 1290], "confidence": 0.991, "entities": [], "pos": [["been", "AUX"]]}, {"text": "modified.", "coordinates": [347, 1254, 536, 1289], "confidence": 0.995, "entities": [], "pos": [["modified", "VERB"], [".", "PUNCT"]]}, {"text": "The", "coordinates": [572, 1253, 632, 1288], "confidence": 0.998, "entities": [], "pos": [["The", "PRON"]]}, {"text": "new", "coordinates": [650, 1253, 713, 1288], "confidence": 0.998, "entities": [], "pos": [["new", "ADJ"]]}, {"text": "\"announcement\"", "coordinates": [733, 1251, 1016, 1287], "confidence": 0.991, "entities": [], "pos": [["\"", "PUNCT"], ["announcement", "NOUN"], ["\"", "PUNCT"]]}, {"text": "action", "coordinates": [1032, 1249, 1152, 1285], "confidence": 0.981, "entities": [], "pos": [["action", "NOUN"]]}, {"text": "standards", "coordinates": [1170, 1248, 1354, 1285], "confidence": 0.995, "entities": [], "pos": [["standards", "NOUN"]]}, {"text": "specify:", "coordinates": [1370, 1245, 1535, 1284], "confidence": 0.971, "entities": [], "pos": [["specify", "VERB"], [":", "PUNCT"]]}, {"text": "Significant", "coordinates": [351, 1324, 573, 1363], "confidence": 0.992, "entities": [], "pos": [["Significant", "ADJ"]]}, {"text": "preference", "coordinates": [591, 1323, 794, 1360], "confidence": 0.995, "entities": [], "pos": [["preference", "NOUN"]]}, {"text": "over", "coordinates": [811, 1323, 893, 1357], "confidence": 0.991, "entities": [], "pos": [["over", "ADV"]]}, {"text": "current", "coordinates": [911, 1321, 1053, 1356], "confidence": 0.996, "entities": [], "pos": [["current", "ADJ"]]}, {"text": "among", "coordinates": [1074, 1320, 1172, 1355], "confidence": 0.997, "entities": [], "pos": [["among", "ADP"]]}, {"text": "WINSTON", "coordinates": [1190, 1319, 1332, 1353], "confidence": 0.996, "entities": [["WINSTON", "GPE"]], "pos": [["WINSTON", "PROPN"]]}, {"text": "smokers.", "coordinates": [1350, 1317, 1511, 1353], "confidence": 0.995, "entities": [], "pos": [["smokers", "NOUN"], [".", "PUNCT"]]}, {"text": "-", "coordinates": [383, 1364, 399, 1387], "confidence": 0.369, "entities": [], "pos": [["-", "PUNCT"]]}, {"text": "Significant", "coordinates": [355, 1392, 575, 1430], "confidence": 0.994, "entities": [], "pos": [["Significant", "ADJ"]]}, {"text": "preference", "coordinates": [591, 1391, 795, 1428], "confidence": 0.995, "entities": [], "pos": [["preference", "NOUN"]]}, {"text": "over", "coordinates": [811, 1391, 893, 1426], "confidence": 0.99, "entities": [], "pos": [["over", "ADV"]]}, {"text": "Marlboro", "coordinates": [911, 1390, 1075, 1424], "confidence": 0.993, "entities": [["Marlboro", "ORG"]], "pos": [["Marlboro", "PROPN"]]}, {"text": "among", "coordinates": [1093, 1388, 1193, 1423], "confidence": 0.996, "entities": [], "pos": [["among", "ADP"]]}, {"text": "WINSTON", "coordinates": [1212, 1387, 1355, 1422], "confidence": 0.996, "entities": [["WINSTON", "GPE"]], "pos": [["WINSTON", "PROPN"]]}, {"text": "smokers.", "coordinates": [1373, 1386, 1529, 1420], "confidence": 0.994, "entities": [], "pos": [["smokers", "NOUN"], [".", "PUNCT"]]}, {"text": "(Additional", "coordinates": [363, 1428, 575, 1465], "confidence": 0.991, "entities": [], "pos": [["(", "PUNCT"], ["Additional", "ADJ"]]}, {"text": "element)", "coordinates": [593, 1428, 746, 1463], "confidence": 0.994, "entities": [], "pos": [["element", "NOUN"], [")", "PUNCT"]]}, {"text": "Parity", "coordinates": [351, 1498, 473, 1533], "confidence": 0.997, "entities": [], "pos": [["Parity", "NOUN"]]}, {"text": "or", "coordinates": [491, 1497, 534, 1532], "confidence": 0.998, "entities": [], "pos": [["or", "CCONJ"]]}, {"text": "better", "coordinates": [550, 1497, 675, 1532], "confidence": 0.997, "entities": [], "pos": [["better", "ADV"]]}, {"text": "vs.", "coordinates": [693, 1496, 758, 1530], "confidence": 0.998, "entities": [], "pos": [["vs.", "ADP"]]}, {"text": "Marlboro", "coordinates": [772, 1494, 935, 1530], "confidence": 0.991, "entities": [["Marlboro", "ORG"]], "pos": [["Marlboro", "PROPN"]]}, {"text": "among", "coordinates": [956, 1493, 1055, 1529], "confidence": 0.997, "entities": [], "pos": [["among", "ADP"]]}, {"text": "Marlboro", "coordinates": [1071, 1492, 1234, 1528], "confidence": 0.994, "entities": [["Marlboro", "ORG"]], "pos": [["Marlboro", "PROPN"]]}, {"text": "and", "coordinates": [1254, 1491, 1313, 1526], "confidence": 0.998, "entities": [], "pos": [["and", "CCONJ"]]}, {"text": "B&H", "coordinates": [1331, 1491, 1392, 1526], "confidence": 0.998, "entities": [], "pos": [["B&H", "NOUN"]]}, {"text": "smokers.", "coordinates": [1412, 1490, 1566, 1526], "confidence": 0.889, "entities": [], "pos": [["smokers", "NOUN"], [".", "PUNCT"]]}, {"text": "(Same", "coordinates": [365, 1533, 455, 1569], "confidence": 0.997, "entities": [], "pos": [["(", "PUNCT"], ["Same", "ADJ"]]}, {"text": "blend", "coordinates": [471, 1532, 574, 1568], "confidence": 0.994, "entities": [], "pos": [["blend", "NOUN"]]}, {"text": "used", "coordinates": [594, 1533, 674, 1567], "confidence": 0.989, "entities": [], "pos": [["used", "VERB"]]}, {"text": "in", "coordinates": [697, 1531, 735, 1566], "confidence": 0.998, "entities": [], "pos": [["in", "ADP"]]}, {"text": "Marlboro", "coordinates": [752, 1530, 916, 1566], "confidence": 0.993, "entities": [["Marlboro", "ORG"]], "pos": [["Marlboro", "PROPN"]]}, {"text": "and", "coordinates": [935, 1530, 996, 1564], "confidence": 0.998, "entities": [], "pos": [["and", "CCONJ"]]}, {"text": "B&H)", "coordinates": [1011, 1529, 1093, 1564], "confidence": 0.991, "entities": [], "pos": [["B&H", "NOUN"], [")", "PUNCT"]]}, {"text": "Preference", "coordinates": [354, 1603, 555, 1639], "confidence": 0.994, "entities": [], "pos": [["Preference", "NOUN"]]}, {"text": "over", "coordinates": [574, 1602, 656, 1637], "confidence": 0.988, "entities": [], "pos": [["over", "ADV"]]}, {"text": "Marlboro", "coordinates": [672, 1600, 837, 1637], "confidence": 0.992, "entities": [["Marlboro", "ORG"]], "pos": [["Marlboro", "PROPN"]]}, {"text": "among", "coordinates": [856, 1599, 956, 1634], "confidence": 0.997, "entities": [], "pos": [["among", "ADP"]]}, {"text": "other", "coordinates": [975, 1598, 1076, 1633], "confidence": 0.998, "entities": [], "pos": [["other", "ADJ"]]}, {"text": "NFF", "coordinates": [1092, 1597, 1156, 1632], "confidence": 0.998, "entities": [["NFF", "ORG"]], "pos": [["NFF", "PROPN"]]}, {"text": "smokers.", "coordinates": [1174, 1595, 1338, 1632], "confidence": 0.972, "entities": [], "pos": [["smokers", "NOUN"], [".", "PUNCT"]]}, {"text": "Preference", "coordinates": [355, 1674, 557, 1707], "confidence": 0.994, "entities": [], "pos": [["Preference", "NOUN"]]}, {"text": "to", "coordinates": [577, 1673, 617, 1706], "confidence": 0.998, "entities": [], "pos": [["to", "PART"]]}, {"text": "be", "coordinates": [634, 1672, 678, 1706], "confidence": 0.998, "entities": [], "pos": [["be", "AUX"]]}, {"text": "maximized", "coordinates": [692, 1669, 877, 1705], "confidence": 0.993, "entities": [], "pos": [["maximized", "VERB"]]}, {"text": "versus", "coordinates": [895, 1668, 1017, 1705], "confidence": 0.997, "entities": [], "pos": [["versus", "ADV"]]}, {"text": "females,", "coordinates": [1037, 1666, 1203, 1704], "confidence": 0.995, "entities": [], "pos": [["females", "NOUN"], [",", "PUNCT"]]}, {"text": "the", "coordinates": [1216, 1666, 1276, 1703], "confidence": 0.998, "entities": [], "pos": [["the", "PRON"]]}, {"text": "primary", "coordinates": [1294, 1665, 1436, 1703], "confidence": 0.996, "entities": [], "pos": [["primary", "ADJ"]]}, {"text": "target", "coordinates": [1456, 1665, 1576, 1702], "confidence": 0.997, "entities": [], "pos": [["target", "NOUN"]]}, {"text": "for", "coordinates": [361, 1708, 416, 1744], "confidence": 0.995, "entities": [], "pos": [["for", "ADP"]]}, {"text": "the", "coordinates": [437, 1708, 497, 1743], "confidence": 0.998, "entities": [], "pos": [["the", "PRON"]]}, {"text": "100mm", "coordinates": [515, 1707, 618, 1742], "confidence": 0.997, "entities": [["100mm", "QUANTITY"]], "pos": [["100", "NUM"], ["mm", "NUM"]]}, {"text": "NFF", "coordinates": [634, 1707, 696, 1741], "confidence": 0.998, "entities": [["NFF", "ORG"]], "pos": [["NFF", "PROPN"]]}, {"text": "category.", "coordinates": [716, 1707, 900, 1743], "confidence": 0.995, "entities": [], "pos": [["category", "NOUN"], [".", "PUNCT"]]}, {"text": "TPM", "coordinates": [359, 1779, 416, 1812], "confidence": 0.998, "entities": [], "pos": [["TPM", "NOUN"]]}, {"text": "at", "coordinates": [438, 1779, 478, 1813], "confidence": 0.998, "entities": [], "pos": [["at", "ADP"]]}, {"text": "17", "coordinates": [498, 1778, 539, 1813], "confidence": 0.991, "entities": [["17", "CARDINAL"]], "pos": [["17", "NUM"]]}, {"text": "mgs", "coordinates": [555, 1778, 619, 1813], "confidence": 0.994, "entities": [["mgs", "ORG"]], "pos": [["mgs", "PROPN"]]}, {"text": "or", "coordinates": [637, 1777, 679, 1812], "confidence": 0.997, "entities": [], "pos": [["or", "CCONJ"]]}, {"text": "less.", "coordinates": [698, 1776, 801, 1811], "confidence": 0.997, "entities": [], "pos": [["less", "ADV"], [".", "PUNCT"]]}, {"text": "Test", "coordinates": [259, 1883, 337, 1915], "confidence": 0.988, "entities": [], "pos": [["Test", "NOUN"]]}, {"text": "Results", "coordinates": [356, 1883, 498, 1915], "confidence": 0.996, "entities": [], "pos": [["Results", "NOUN"]]}, {"text": "50886", "coordinates": [1643, 1909, 1676, 2013], "confidence": 0.996, "entities": [["50886", "DATE"]], "pos": [["50886", "NUM"]]}, {"text": "5270", "coordinates": [1644, 2035, 1676, 2114], "confidence": 0.989, "entities": [["5270", "DATE"]], "pos": [["5270", "NUM"]]}, {"text": "Blend", "coordinates": [256, 1953, 360, 1987], "confidence": 0.997, "entities": [], "pos": [["Blend", "PROPN"]]}, {"text": "#2", "coordinates": [379, 1952, 420, 1987], "confidence": 0.982, "entities": [["2", "MONEY"]], "pos": [["#", "SYM"], ["2", "NUM"]]}, {"text": "demonstrated", "coordinates": [437, 1950, 680, 1986], "confidence": 0.991, "entities": [], "pos": [["demonstrated", "VERB"]]}, {"text": "significant", "coordinates": [700, 1948, 922, 1984], "confidence": 0.994, "entities": [], "pos": [["significant", "ADJ"]]}, {"text": "advantages", "coordinates": [939, 1946, 1139, 1983], "confidence": 0.995, "entities": [], "pos": [["advantages", "NOUN"]]}, {"text": "over", "coordinates": [1159, 1946, 1240, 1981], "confidence": 0.989, "entities": [], "pos": [["over", "ADV"]]}, {"text": "current", "coordinates": [1260, 1945, 1401, 1980], "confidence": 0.997, "entities": [], "pos": [["current", "ADJ"]]}, {"text": "WINSTON", "coordinates": [1417, 1944, 1558, 1979], "confidence": 0.996, "entities": [["WINSTON", "GPE"]], "pos": [["WINSTON", "PROPN"]]}, {"text": "100's,", "coordinates": [259, 1988, 381, 2023], "confidence": 0.938, "entities": [["100", "CARDINAL"]], "pos": [["100", "NUM"], ["'s", "PART"], [",", "PUNCT"]]}, {"text": "although", "coordinates": [399, 1987, 558, 2021], "confidence": 0.995, "entities": [], "pos": [["although", "SCONJ"]]}, {"text": "the", "coordinates": [578, 1985, 640, 2020], "confidence": 0.997, "entities": [], "pos": [["the", "PRON"]]}, {"text": "blend", "coordinates": [655, 1984, 760, 2020], "confidence": 0.997, "entities": [], "pos": [["blend", "NOUN"]]}, {"text": "did", "coordinates": [778, 1984, 840, 2019], "confidence": 0.998, "entities": [], "pos": [["did", "VERB"]]}, {"text": "not", "coordinates": [857, 1982, 919, 2018], "confidence": 0.998, "entities": [], "pos": [["not", "PART"]]}, {"text": "fully", "coordinates": [938, 1981, 1039, 2017], "confidence": 0.998, "entities": [], "pos": [["fully", "ADV"]]}, {"text": "meet", "coordinates": [1054, 1981, 1139, 2016], "confidence": 0.991, "entities": [], "pos": [["meet", "VERB"]]}, {"text": "the", "coordinates": [1158, 1980, 1221, 2015], "confidence": 0.998, "entities": [], "pos": [["the", "PRON"]]}, {"text": "action", "coordinates": [1237, 1979, 1359, 2015], "confidence": 0.997, "entities": [], "pos": [["action", "NOUN"]]}, {"text": "standards", "coordinates": [1378, 1977, 1559, 2013], "confidence": 0.995, "entities": [], "pos": [["standards", "NOUN"]]}, {"text": "for", "coordinates": [262, 2025, 320, 2057], "confidence": 0.998, "entities": [], "pos": [["for", "ADP"]]}, {"text": "\"announcement\"", "coordinates": [340, 2021, 623, 2056], "confidence": 0.905, "entities": [], "pos": [["\"", "PUNCT"], ["announcement", "NOUN"], ["\"", "PUNCT"]]}, {"text": "test", "coordinates": [639, 2020, 722, 2055], "confidence": 0.996, "entities": [], "pos": [["test", "NOUN"]]}, {"text": "market.", "coordinates": [738, 2018, 884, 2055], "confidence": 0.995, "entities": [], "pos": [["market", "NOUN"], [".", "PUNCT"]]}, {"text": "Test", "coordinates": [921, 2017, 1002, 2053], "confidence": 0.989, "entities": [], "pos": [["Test", "NOUN"]]}, {"text": "results", "coordinates": [1018, 2015, 1162, 2053], "confidence": 0.995, "entities": [], "pos": [["results", "NOUN"]]}, {"text": "indicated", "coordinates": [1180, 2013, 1361, 2052], "confidence": 0.995, "entities": [], "pos": [["indicated", "VERB"]]}, {"text": "that", "coordinates": [1379, 2012, 1460, 2050], "confidence": 0.989, "entities": [], "pos": [["that", "SCONJ"]]}, {"text": "blend", "coordinates": [1476, 2010, 1580, 2049], "confidence": 0.997, "entities": [], "pos": [["blend", "NOUN"]]}, {"text": "#2", "coordinates": [262, 2059, 300, 2092], "confidence": 0.994, "entities": [["2", "MONEY"]], "pos": [["#", "SYM"], ["2", "NUM"]]}, {"text": "was:", "coordinates": [316, 2060, 401, 2091], "confidence": 0.969, "entities": [], "pos": [["was", "AUX"], [":", "PUNCT"]]}]