[{"text": "From:", "coordinates": [254, 202, 341, 241], "confidence": 0.994, "entities": [], "pos": [["From", "ADP"], [":", "PUNCT"]]}, {"text": "Etzel,", "coordinates": [348, 202, 424, 242], "confidence": 0.894, "entities": [], "pos": [["Etzel", "PROPN"], [",", "PUNCT"]]}, {"text": "Emily", "coordinates": [432, 202, 513, 245], "confidence": 0.998, "entities": [], "pos": [["Emily", "ADV"]]}, {"text": "C.", "coordinates": [521, 203, 558, 246], "confidence": 0.994, "entities": [], "pos": [["C.", "PROPN"]]}, {"text": "To:", "coordinates": [262, 243, 306, 280], "confidence": 0.998, "entities": [], "pos": [["To", "ADP"], [":", "PUNCT"]]}, {"text": "Weber,", "coordinates": [312, 243, 408, 281], "confidence": 0.995, "entities": [], "pos": [["Weber", "PROPN"], [",", "PUNCT"]]}, {"text": "Doug", "coordinates": [414, 245, 493, 282], "confidence": 0.988, "entities": [], "pos": [["Doug", "PROPN"]]}, {"text": "CC:", "coordinates": [257, 286, 315, 316], "confidence": 0.991, "entities": [], "pos": [["CC", "NOUN"], [":", "PUNCT"]]}, {"text": "BCC:", "coordinates": [254, 324, 339, 357], "confidence": 0.987, "entities": [["BCC", "ORG"]], "pos": [["BCC", "NOUN"], [":", "PUNCT"]]}, {"text": "Primary", "coordinates": [263, 364, 372, 399], "confidence": 0.994, "entities": [], "pos": [["Primary", "ADJ"]]}, {"text": "Date:", "coordinates": [378, 363, 456, 398], "confidence": 0.996, "entities": [], "pos": [["Date", "NOUN"], [":", "PUNCT"]]}, {"text": "8/20/1996", "coordinates": [462, 363, 602, 398], "confidence": 0.995, "entities": [["8/20/1996", "DATE"]], "pos": [["8/20/1996", "NUM"]]}, {"text": "1:04:00", "coordinates": [607, 362, 707, 397], "confidence": 0.995, "entities": [["1:04:00", "CARDINAL"]], "pos": [["1:04:00", "NUM"]]}, {"text": "PM", "coordinates": [712, 361, 754, 397], "confidence": 0.998, "entities": [], "pos": [["PM", "NOUN"]]}, {"text": "Last", "coordinates": [254, 403, 315, 438], "confidence": 0.994, "entities": [], "pos": [["Last", "ADJ"]]}, {"text": "Modified", "coordinates": [322, 402, 452, 438], "confidence": 0.996, "entities": [], "pos": [["Modified", "VERB"]]}, {"text": "Date:", "coordinates": [459, 402, 539, 437], "confidence": 0.998, "entities": [], "pos": [["Date", "NOUN"], [":", "PUNCT"]]}, {"text": "2001-Nov-20", "coordinates": [546, 402, 724, 438], "confidence": 0.994, "entities": [["2001-Nov-20", "DATE"]], "pos": [["2001", "NUM"], ["-", "PUNCT"], ["Nov-20", "NOUN"]]}, {"text": "14:43:48", "coordinates": [731, 403, 852, 438], "confidence": 0.995, "entities": [["14:43:48", "TIME"]], "pos": [["14:43:48", "NUM"]]}, {"text": "Last", "coordinates": [254, 444, 319, 478], "confidence": 0.988, "entities": [], "pos": [["Last", "ADJ"]]}, {"text": "Touched", "coordinates": [326, 445, 448, 479], "confidence": 0.997, "entities": [], "pos": [["Touched", "VERB"]]}, {"text": "Date:", "coordinates": [453, 446, 541, 479], "confidence": 0.995, "entities": [], "pos": [["Date", "NOUN"], [":", "PUNCT"]]}, {"text": "Sent", "coordinates": [255, 483, 316, 517], "confidence": 0.994, "entities": [], "pos": [["Sent", "VERB"]]}, {"text": "Date:", "coordinates": [323, 483, 404, 517], "confidence": 0.997, "entities": [], "pos": [["Date", "NOUN"], [":", "PUNCT"]]}, {"text": "1996-Aug-20", "coordinates": [411, 483, 587, 517], "confidence": 0.994, "entities": [["1996-Aug-20", "DATE"]], "pos": [["1996", "NUM"], ["-", "PUNCT"], ["Aug-20", "NUM"]]}, {"text": "13:01:00", "coordinates": [595, 483, 713, 517], "confidence": 0.996, "entities": [["13:01:00", "TIME"]], "pos": [["13:01:00", "NUM"]]}, {"text": "Received", "coordinates": [257, 521, 379, 556], "confidence": 0.995, "entities": [], "pos": [["Received", "VERB"]]}, {"text": "Date:", "coordinates": [385, 521, 466, 556], "confidence": 0.997, "entities": [], "pos": [["Date", "NOUN"], [":", "PUNCT"]]}, {"text": "1996-Aug-20", "coordinates": [473, 521, 650, 557], "confidence": 0.994, "entities": [["1996-Aug-20", "DATE"]], "pos": [["1996", "NUM"], ["-", "PUNCT"], ["Aug-20", "NUM"]]}, {"text": "13:04:00", "coordinates": [657, 522, 776, 556], "confidence": 0.996, "entities": [["13:04:00", "PERSON"]], "pos": [["13:04:00", "NUM"]]}, {"text": "Subject:", "coordinates": [256, 561, 374, 597], "confidence": 0.994, "entities": [], "pos": [["Subject", "NOUN"], [":", "PUNCT"]]}, {"text": "TESTMKT.XLS", "coordinates": [380, 563, 603, 597], "confidence": 0.976, "entities": [], "pos": [["TESTMKT.XLS", "ADV"]]}, {"text": "Attachments:", "coordinates": [257, 644, 444, 677], "confidence": 0.991, "entities": [], "pos": [["Attachments", "NOUN"], [":", "PUNCT"]]}, {"text": "TESTMKT.XLS", "coordinates": [256, 679, 481, 716], "confidence": 0.881, "entities": [], "pos": [["TESTMKT.XLS", "ADV"]]}, {"text": "Doug,", "coordinates": [256, 803, 343, 836], "confidence": 0.994, "entities": [], "pos": [["Doug", "PROPN"], [",", "PUNCT"]]}, {"text": "Here", "coordinates": [251, 879, 317, 914], "confidence": 0.648, "entities": [], "pos": [["Here", "ADV"]]}, {"text": "is", "coordinates": [322, 879, 348, 915], "confidence": 0.998, "entities": [], "pos": [["is", "AUX"]]}, {"text": "the", "coordinates": [352, 879, 397, 915], "confidence": 0.993, "entities": [], "pos": [["the", "PRON"]]}, {"text": "corrected", "coordinates": [402, 879, 527, 915], "confidence": 0.973, "entities": [], "pos": [["corrected", "VERB"]]}, {"text": "sheet.", "coordinates": [531, 879, 611, 915], "confidence": 0.994, "entities": [], "pos": [["sheet", "NOUN"], [".", "PUNCT"]]}, {"text": "I", "coordinates": [616, 879, 628, 915], "confidence": 0.997, "entities": [], "pos": [["I", "PRON"]]}, {"text": "noticed", "coordinates": [632, 879, 731, 916], "confidence": 0.994, "entities": [], "pos": [["noticed", "VERB"]]}, {"text": "that", "coordinates": [736, 879, 790, 916], "confidence": 0.981, "entities": [], "pos": [["that", "SCONJ"]]}, {"text": "you", "coordinates": [795, 879, 846, 916], "confidence": 0.998, "entities": [], "pos": [["you", "PRON"]]}, {"text": "changed", "coordinates": [851, 880, 964, 916], "confidence": 0.996, "entities": [], "pos": [["changed", "VERB"]]}, {"text": "the", "coordinates": [969, 880, 1011, 916], "confidence": 0.996, "entities": [], "pos": [["the", "PRON"]]}, {"text": "September,", "coordinates": [1016, 880, 1168, 916], "confidence": 0.95, "entities": [["September", "DATE"]], "pos": [["September", "PROPN"], [",", "PUNCT"]]}, {"text": "'96", "coordinates": [1174, 880, 1213, 916], "confidence": 0.958, "entities": [["'96", "DATE"]], "pos": [["'", "NUM"], ["96", "NUM"]]}, {"text": "introductions", "coordinates": [1219, 880, 1397, 916], "confidence": 0.967, "entities": [], "pos": [["introductions", "NOUN"]]}, {"text": "of", "coordinates": [256, 919, 282, 953], "confidence": 0.998, "entities": [], "pos": [["of", "ADP"]]}, {"text": "Kamel", "coordinates": [288, 919, 377, 954], "confidence": 0.997, "entities": [["Kamel", "ORG"]], "pos": [["Kamel", "NOUN"]]}, {"text": "to", "coordinates": [384, 919, 410, 954], "confidence": 0.998, "entities": [], "pos": [["to", "PART"]]}, {"text": "October.", "coordinates": [416, 919, 535, 955], "confidence": 0.995, "entities": [["October", "DATE"]], "pos": [["October", "PROPN"], [".", "PUNCT"]]}, {"text": "The", "coordinates": [541, 919, 591, 955], "confidence": 0.994, "entities": [], "pos": [["The", "PRON"]]}, {"text": "Sales", "coordinates": [597, 919, 667, 956], "confidence": 0.998, "entities": [], "pos": [["Sales", "NOUN"]]}, {"text": "Force", "coordinates": [674, 919, 753, 956], "confidence": 0.994, "entities": [], "pos": [["Force", "NOUN"]]}, {"text": "will", "coordinates": [760, 919, 811, 956], "confidence": 0.989, "entities": [], "pos": [["will", "AUX"]]}, {"text": "be", "coordinates": [818, 919, 848, 956], "confidence": 0.997, "entities": [], "pos": [["be", "AUX"]]}, {"text": "beginning", "coordinates": [855, 919, 990, 956], "confidence": 0.995, "entities": [], "pos": [["beginning", "VERB"]]}, {"text": "to", "coordinates": [996, 920, 1022, 956], "confidence": 0.998, "entities": [], "pos": [["to", "PART"]]}, {"text": "spread", "coordinates": [1029, 920, 1117, 956], "confidence": 0.942, "entities": [], "pos": [["spread", "VERB"]]}, {"text": "in", "coordinates": [1124, 920, 1150, 956], "confidence": 0.997, "entities": [], "pos": [["in", "ADP"]]}, {"text": "September", "coordinates": [1157, 920, 1307, 956], "confidence": 0.995, "entities": [["September", "DATE"]], "pos": [["September", "PROPN"]]}, {"text": "according", "coordinates": [254, 960, 384, 995], "confidence": 0.991, "entities": [], "pos": [["according", "VERB"]]}, {"text": "to", "coordinates": [388, 960, 419, 994], "confidence": 0.998, "entities": [], "pos": [["to", "PART"]]}, {"text": "Brice", "coordinates": [423, 960, 497, 994], "confidence": 0.997, "entities": [], "pos": [["Brice", "NOUN"]]}, {"text": "and", "coordinates": [502, 960, 552, 994], "confidence": 0.998, "entities": [], "pos": [["and", "CCONJ"]]}, {"text": "Lawrence.", "coordinates": [557, 960, 694, 994], "confidence": 0.994, "entities": [["Lawrence", "PERSON"]], "pos": [["Lawrence", "PROPN"], [".", "PUNCT"]]}, {"text": "Also", "coordinates": [257, 1038, 316, 1073], "confidence": 0.991, "entities": [], "pos": [["Also", "ADV"]]}, {"text": "I", "coordinates": [322, 1038, 336, 1073], "confidence": 0.998, "entities": [], "pos": [["I", "PRON"]]}, {"text": "am", "coordinates": [342, 1038, 378, 1072], "confidence": 0.998, "entities": [], "pos": [["am", "AUX"]]}, {"text": "sending", "coordinates": [389, 1037, 495, 1072], "confidence": 0.997, "entities": [], "pos": [["sending", "VERB"]]}, {"text": "a", "coordinates": [500, 1037, 515, 1072], "confidence": 0.995, "entities": [], "pos": [["a", "PRON"]]}, {"text": "longer", "coordinates": [521, 1037, 607, 1072], "confidence": 0.997, "entities": [], "pos": [["longer", "ADV"]]}, {"text": "list", "coordinates": [612, 1037, 656, 1072], "confidence": 0.988, "entities": [], "pos": [["list", "NOUN"]]}, {"text": "of", "coordinates": [661, 1037, 692, 1072], "confidence": 0.998, "entities": [], "pos": [["of", "ADP"]]}, {"text": "markets", "coordinates": [697, 1037, 804, 1072], "confidence": 0.996, "entities": [], "pos": [["markets", "NOUN"]]}, {"text": "that", "coordinates": [809, 1037, 862, 1072], "confidence": 0.988, "entities": [], "pos": [["that", "SCONJ"]]}, {"text": "you", "coordinates": [867, 1038, 916, 1072], "confidence": 0.998, "entities": [], "pos": [["you", "PRON"]]}, {"text": "may", "coordinates": [921, 1038, 981, 1072], "confidence": 0.998, "entities": [], "pos": [["may", "AUX"]]}, {"text": "or", "coordinates": [986, 1038, 1017, 1072], "confidence": 0.998, "entities": [], "pos": [["or", "CCONJ"]]}, {"text": "may", "coordinates": [1022, 1038, 1079, 1072], "confidence": 0.998, "entities": [], "pos": [["may", "AUX"]]}, {"text": "not", "coordinates": [1084, 1039, 1131, 1073], "confidence": 0.998, "entities": [], "pos": [["not", "PART"]]}, {"text": "want", "coordinates": [1136, 1039, 1202, 1073], "confidence": 0.989, "entities": [], "pos": [["want", "VERB"]]}, {"text": "to", "coordinates": [1207, 1040, 1236, 1073], "confidence": 0.998, "entities": [], "pos": [["to", "PART"]]}, {"text": "add", "coordinates": [1241, 1040, 1292, 1073], "confidence": 0.998, "entities": [], "pos": [["add", "VERB"]]}, {"text": "to", "coordinates": [1297, 1040, 1328, 1073], "confidence": 0.998, "entities": [], "pos": [["to", "PART"]]}, {"text": "your", "coordinates": [1332, 1041, 1398, 1074], "confidence": 0.989, "entities": [], "pos": [["your", "PRON"]]}, {"text": "list", "coordinates": [258, 1076, 294, 1111], "confidence": 0.982, "entities": [], "pos": [["list", "NOUN"]]}, {"text": "(now", "coordinates": [301, 1076, 368, 1112], "confidence": 0.987, "entities": [], "pos": [["(", "PUNCT"], ["now", "ADV"]]}, {"text": "that", "coordinates": [376, 1075, 427, 1112], "confidence": 0.982, "entities": [], "pos": [["that", "SCONJ"]]}, {"text": "you", "coordinates": [435, 1075, 483, 1112], "confidence": 0.998, "entities": [], "pos": [["you", "PRON"]]}, {"text": "have", "coordinates": [490, 1075, 554, 1113], "confidence": 0.991, "entities": [], "pos": [["have", "VERB"]]}, {"text": "extended", "coordinates": [561, 1075, 678, 1113], "confidence": 0.995, "entities": [], "pos": [["extended", "VERB"]]}, {"text": "beyond", "coordinates": [685, 1075, 785, 1113], "confidence": 0.997, "entities": [], "pos": [["beyond", "ADP"]]}, {"text": "just", "coordinates": [792, 1075, 838, 1113], "confidence": 0.988, "entities": [], "pos": [["just", "ADV"]]}, {"text": "the", "coordinates": [845, 1075, 887, 1113], "confidence": 0.998, "entities": [], "pos": [["the", "PRON"]]}, {"text": "regions.", "coordinates": [894, 1075, 999, 1113], "confidence": 0.994, "entities": [], "pos": [["regions", "NOUN"], [".", "PUNCT"]]}, {"text": "I", "coordinates": [1006, 1075, 1018, 1113], "confidence": 0.995, "entities": [], "pos": [["I", "PRON"]]}, {"text": "will", "coordinates": [1025, 1075, 1076, 1113], "confidence": 0.989, "entities": [], "pos": [["will", "AUX"]]}, {"text": "send", "coordinates": [1084, 1075, 1144, 1113], "confidence": 0.988, "entities": [], "pos": [["send", "VERB"]]}, {"text": "them", "coordinates": [1152, 1076, 1214, 1113], "confidence": 0.987, "entities": [], "pos": [["them", "PRON"]]}, {"text": "via", "coordinates": [1227, 1076, 1268, 1113], "confidence": 0.998, "entities": [], "pos": [["via", "ADP"]]}, {"text": "a", "coordinates": [1276, 1076, 1290, 1113], "confidence": 0.996, "entities": [], "pos": [["a", "PRON"]]}, {"text": "separate", "coordinates": [1297, 1076, 1412, 1113], "confidence": 0.951, "entities": [], "pos": [["separate", "ADJ"]]}, {"text": "c-mail.", "coordinates": [259, 1116, 350, 1151], "confidence": 0.888, "entities": [], "pos": [["c", "NOUN"], ["-", "NOUN"], ["mail", "NOUN"], [".", "PUNCT"]]}, {"text": "Emily", "coordinates": [254, 1231, 343, 1270], "confidence": 0.994, "entities": [], "pos": [["Emily", "ADV"]]}, {"text": "53048", "coordinates": [1556, 1955, 1599, 2064], "confidence": 0.998, "entities": [["53048", "CARDINAL"]], "pos": [["53048", "NUM"]]}, {"text": "9046", "coordinates": [1563, 2075, 1606, 2165], "confidence": 0.98, "entities": [["9046", "DATE"]], "pos": [["9046", "NUM"]]}, {"text": "RJR0000000520039592", "coordinates": [24, 2179, 379, 2215], "confidence": 0.958, "entities": [], "pos": [["RJR0000000520039592", "PROPN"]]}, {"text": "70058", "coordinates": [25, 2220, 113, 2255], "confidence": 0.996, "entities": [["70058", "DATE"]], "pos": [["70058", "NUM"]]}, {"text": "9777", "coordinates": [121, 2221, 199, 2255], "confidence": 0.991, "entities": [["9777", "CARDINAL"]], "pos": [["9777", "NUM"]]}]